torxtools/__init__.py
torxtools/argtools.py
torxtools/cfgtools.py
torxtools/ctxtools.py
torxtools/dicttools.py
torxtools/locktools.py
torxtools/pathtools.py
torxtools/testtools.py
torxtools/xdgtools.py
torxtools/testing/__init__.py
torxtools-1.2.0.dist-info/LICENSE
torxtools-1.2.0.dist-info/METADATA
torxtools-1.2.0.dist-info/WHEEL
torxtools-1.2.0.dist-info/entry_points.txt
torxtools-1.2.0.dist-info/top_level.txt
torxtools-1.2.0.dist-info/zip-safe
torxtools-1.2.0.dist-info/RECORD
