Metadata-Version: 2.1
Name: torxtools
Version: 1.2.0
Summary: Less generic functionalities than Phillips and Pozidriv tools. One size fits most. MacGyver's French army spork.
Author-email: Julien Lecomte <julien@lecomte.at>
License: MIT
Project-URL: Homepage, https://gitlab.com/cappysan/torxtools
Project-URL: Documentation, https://torxtools.docs.cappysan.dev
Project-URL: Source code, https://gitlab.com/cappysan/torxtools
Project-URL: Bug tracker, https://gitlab.com/cappysan/torxtools/-/issues
Classifier: Development Status :: 5 - Production/Stable
Classifier: Intended Audience :: Developers
Classifier: License :: OSI Approved :: MIT License
Classifier: Programming Language :: Python :: 3 :: Only
Classifier: Topic :: Software Development :: Libraries
Classifier: Topic :: Utilities
Classifier: Programming Language :: Python :: 3.7
Classifier: Programming Language :: Python :: 3.8
Classifier: Programming Language :: Python :: 3.9
Classifier: Programming Language :: Python :: 3.10
Classifier: Programming Language :: Python :: 3.11
Classifier: Programming Language :: Python :: 3.12
Requires-Python: >=3.7
License-File: LICENSE
Requires-Dist: boltons>=19.3
Requires-Dist: filelock>=3.0
Requires-Dist: xdg>=5.0
Provides-Extra: dev
